superset_wfs_dialect/__init__.py
superset_wfs_dialect/base.py
superset_wfs_dialect/dialect.py
superset_wfs_dialect/exceptions.py
superset_wfs_dialect/gml_geoms.py
superset_wfs_dialect/gml_parser.py
superset_wfs_dialect/namespaces.py
superset_wfs_dialect/sql_logger.py
superset_wfs_dialect/wkt_parser.py
superset_wfs_dialect/tests/__init__.py
superset_wfs_dialect/tests/conftest.py
superset_wfs_dialect/tests/test_base.py
superset_wfs_dialect/tests/test_dialect.py
superset_wfs_dialect/tests/test_get_filter_from_expression.py
superset_wfs_dialect/tests/test_gml_parser.py
superset_wfs_dialect/tests/test_sql_logger.py
superset_wfs_dialect/tests/test_wkt_parser.py
superset_wfs_dialect-0.0.12.dist-info/licenses/LICENSE
superset_wfs_dialect-0.0.12.dist-info/licenses/NOTICE
superset_wfs_dialect-0.0.12.dist-info/METADATA
superset_wfs_dialect-0.0.12.dist-info/WHEEL
superset_wfs_dialect-0.0.12.dist-info/entry_points.txt
superset_wfs_dialect-0.0.12.dist-info/top_level.txt
superset_wfs_dialect-0.0.12.dist-info/RECORD
