Metadata-Version: 2.4
Name: superset_wfs_dialect
Version: 0.0.12
Summary: SQLAlchemy dialect for OGC WFS
Home-page: https://github.com/terrestris/superset_wfs_dialect
Author: terrestris GmbH & Co. KG
Author-email: info@terrestris.de
License: Apache-2.0
Requires-Python: >=3.10
License-File: LICENSE
License-File: NOTICE
Requires-Dist: sqlalchemy==1.4.49
Requires-Dist: requests>=2.32.3
Requires-Dist: sqlglot>=21.0.0
Requires-Dist: debugpy>=1.8.14
Requires-Dist: lxml>=5.4.0
Requires-Dist: OWSLib>=0.34.0
Requires-Dist: pyproj>=3.7.1
Requires-Dist: orjson>=3.11.4
Dynamic: author
Dynamic: author-email
Dynamic: description
Dynamic: description-content-type
Dynamic: home-page
Dynamic: license
Dynamic: license-file
Dynamic: requires-dist
Dynamic: requires-python
Dynamic: summary
